odoo/addons/website_event_membership_restriction/README.rst
odoo/addons/website_event_membership_restriction/__init__.py
odoo/addons/website_event_membership_restriction/__manifest__.py
odoo/addons/website_event_membership_restriction/data/website_event_membership_info.xml
odoo/addons/website_event_membership_restriction/i18n/es.po
odoo/addons/website_event_membership_restriction/i18n/it.po
odoo/addons/website_event_membership_restriction/i18n/website_event_membership_restriction.pot
odoo/addons/website_event_membership_restriction/models/__init__.py
odoo/addons/website_event_membership_restriction/models/event_event.py
odoo/addons/website_event_membership_restriction/readme/CONFIGURE.md
odoo/addons/website_event_membership_restriction/readme/CONTRIBUTORS.md
odoo/addons/website_event_membership_restriction/readme/DESCRIPTION.md
odoo/addons/website_event_membership_restriction/readme/USAGE.md
odoo/addons/website_event_membership_restriction/static/description/icon.png
odoo/addons/website_event_membership_restriction/static/description/index.html
odoo/addons/website_event_membership_restriction/views/event_event_views.xml
odoo/addons/website_event_membership_restriction/views/event_templates.xml
odoo_addon_website_event_membership_restriction-18.0.1.0.0.2.dist-info/METADATA
odoo_addon_website_event_membership_restriction-18.0.1.0.0.2.dist-info/WHEEL
odoo_addon_website_event_membership_restriction-18.0.1.0.0.2.dist-info/top_level.txt
odoo_addon_website_event_membership_restriction-18.0.1.0.0.2.dist-info/RECORD
