Metadata-Version: 2.1
Name: odoo-addon-website_event_membership_restriction
Version: 18.0.1.0.0.2
Requires-Python: >=3.10
Requires-Dist: odoo==18.0.*
Summary: Restrict event registration to members only
Home-page: https://github.com/OCA/event
License: LGPL-3
Author: Tecnativa, Odoo Community Association (OCA)
Author-email: support@odoo-community.org
Classifier: Programming Language :: Python
Classifier: Framework :: Odoo
Classifier: Framework :: Odoo :: 18.0
Classifier: License :: OSI Approved :: GNU Lesser General Public License v3 (LGPLv3)
